pyduckling_native_phihos-0.3.0.dist-info/METADATA
pyduckling_native_phihos-0.3.0.dist-info/WHEEL
duckling.libs/libgcc_s-a0b57c20.so.1
duckling.libs/libgmp-e9987f27.so.10
duckling.libs/libpcre-1bfc3cc8.so.1
duckling/duckling.pyi
duckling/tests/__init__.py
duckling/tests/test_duckling.py
duckling/__init__.py
duckling/duckling.cpython-38-x86_64-linux-gnu.so
pyduckling_native_phihos-0.3.0.dist-info/RECORD
