Metadata-Version: 2.4
Name: pyduckling-native-phihos
Version: 0.3.0
Summary: Rust-based Python wrapper for duckling library in Haskell.
Keywords: haskell,python,parse,duckling
Author: Edgar Andrés Margffoy Tuay <andfoy@gmail.com>, Philipp Hossner <philipp.hossner@posteo.de>
Author-email: Edgar Andrés Margffoy Tuay <andfoy@gmail.com>, Philipp Hossner <philipp.hossner@posteo.de>
License: MIT
Project-URL: Source Code, https://github.com/phihos/pyduckling
